db_able/__init__.py
db_able/creatable.py
db_able/deletable.py
db_able/listable.py
db_able/loadable.py
db_able/savable.py
db_able/base_model/__init__.py
db_able/base_model/database_abc.py
db_able/base_model/kwargs_validator.py
db_able/base_model/params.py
db_able/client/__init__.py
db_able/mgmt/__init__.py
db_able/mgmt/const.py
db_able/utils/__init__.py
db_able/utils/sql_generator.py
examples/__init__.py
examples/a.py
examples/b.py
examples/c.py
examples/user.py
tests/__init__.py
tests/conftest.py
tests/test_client.py
tests/test_db_able.py
tests/base_model/__init__.py
tests/base_model/test_database_abc.py
tests/base_model/test_kwargs_validator.py
tests/base_model/test_params.py
tests/utils/__init__.py
tests/utils/test_sql_generator.py
db_able-2.1.6.dist-info/LICENSE
db_able-2.1.6.dist-info/METADATA
db_able-2.1.6.dist-info/WHEEL
db_able-2.1.6.dist-info/top_level.txt
db_able-2.1.6.dist-info/RECORD
