Metadata-Version: 2.1
Name: db-able
Version: 2.1.6
Summary: Implement basic CRUD operations into DataObject framework with generalized DB access.
Home-page: https://github.com/timdaviss/db-able
Author: Tim Davis
Author-email: timdavis.3991@gmail.com
License: UNKNOWN
Keywords: development,OO
Platform: UNKNOWN
Classifier: Development Status :: 3 - Alpha
Classifier: Intended Audience :: Developers
Classifier: Topic :: Software Development :: Build Tools
Classifier: Operating System :: OS Independent
Classifier: License :: OSI Approved :: MIT License
Classifier: Programming Language :: Python
Classifier: Programming Language :: Python :: 3.9
License-File: LICENSE
Requires-Dist: do-py (>=0.3)
Requires-Dist: sqlalchemy (>=1)
Requires-Dist: pymysql (>=1)
Requires-Dist: pyhumps (>=3)
